setup.py
stanley_outlet_control/__init__.py
stanley_outlet_control/stanley_controller.py
stanley_outlet_control.egg-info/PKG-INFO
stanley_outlet_control.egg-info/SOURCES.txt
stanley_outlet_control.egg-info/dependency_links.txt
stanley_outlet_control.egg-info/entry_points.txt
stanley_outlet_control.egg-info/pbr.json
stanley_outlet_control.egg-info/top_level.txt