Metadata-Version: 1.1
Name: stanley-outlet-control
Version: 1.0.1
Summary: Remotely control your remotely-controlled Stanley AC outlets using a hackrf.
Home-page: https://github.com/coddingtonbear/stanley-outlet-control
Author: Adam Coddington
Author-email: me@adamcoddington.net
License: UNKNOWN
Platform: UNKNOWN
Classifier: License :: OSI Approved :: MIT License
Classifier: Operating System :: OS Independent
Classifier: Programming Language :: Python :: 3
